[
  {
    "channel": "CCTV-1高清",
    "address": "http://ivi.bupt.edu.cn/hls/cctv1hd.m3u8"
  },
  {
    "channel": "CCTV-2高清",
    "address": "http://ivi.bupt.edu.cn/hls/cctv2hd.m3u8"
  },
  {
    "channel": "CCTV-3高清",
    "address": "http://ivi.bupt.edu.cn/hls/cctv3hd.m3u8"
  },
  {
    "channel": "CCTV-4高清",
    "address": "http://ivi.bupt.edu.cn/hls/cctv4hd.m3u8"
  },
  {
    "channel": "CCTV-5+高清",
    "address": "http://ivi.bupt.edu.cn/hls/cctv5phd.m3u8"
  },
  {
    "channel": "CCTV-6高清",
    "address": "http://ivi.bupt.edu.cn/hls/cctv6hd.m3u8"
  },
  {
    "channel": "CCTV-7高清",
    "address": "http://ivi.bupt.edu.cn/hls/cctv7hd.m3u8"
  },
  {
    "channel": "CCTV-8高清",
    "address": "http://ivi.bupt.edu.cn/hls/cctv8hd.m3u8"
  },
  {
    "channel": "CCTV-9高清",
    "address": "http://ivi.bupt.edu.cn/hls/cctv9hd.m3u8"
  },
  {
    "channel": "CCTV-10高清",
    "address": "http://ivi.bupt.edu.cn/hls/cctv10hd.m3u8"
  },
  {
    "channel": "CCTV-12高清",
    "address": "http://ivi.bupt.edu.cn/hls/cctv12hd.m3u8"
  },
  {
    "channel": "CCTV-13高清",
    "address": "http://ivi.bupt.edu.cn/hls/cctv13hd.m3u8"
  },
  {
    "channel": "CCTV-14高清",
    "address": "http://ivi.bupt.edu.cn/hls/cctv14hd.m3u8"
  },
  {
    "channel": "CCTV-17高清",
    "address": "http://ivi.bupt.edu.cn/hls/cctv17hd.m3u8"
  },
  {
    "channel": "北京卫视高清",
    "address": "http://ivi.bupt.edu.cn/hls/btv1hd.m3u8"
  },
  {
    "channel": "湖南卫视高清",
    "address": "http://ivi.bupt.edu.cn/hls/hunanhd.m3u8"
  },
  {
    "channel": "浙江卫视高清",
    "address": "http://125.210.152.18:9090/live/ZJWSHD_H265.m3u8"
  },
  {
    "channel": "江苏卫视高清",
    "address": "http://ivi.bupt.edu.cn/hls/jshd.m3u8"
  },
  {
    "channel": "东方卫视高清",
    "address": "http://ivi.bupt.edu.cn/hls/dfhd.m3u8"
  },
  {
    "channel": "安徽卫视高清",
    "address": "http://ivi.bupt.edu.cn/hls/ahhd.m3u8"
  },
  {
    "channel": "黑龙江卫视高清",
    "address": "http://ivi.bupt.edu.cn/hls/hljhd.m3u8"
  },
  {
    "channel": "辽宁卫视高清",
    "address": "http://ivi.bupt.edu.cn/hls/lnhd.m3u8"
  },
  {
    "channel": "深圳卫视高清",
    "address": "http://ivi.bupt.edu.cn/hls/szhd.m3u8"
  },
  {
    "channel": "广东卫视高清",
    "address": "http://ivi.bupt.edu.cn/hls/gdhd.m3u8"
  },
  {
    "channel": "天津卫视高清",
    "address": "http://ivi.bupt.edu.cn/hls/tjhd.m3u8"
  },
  {
    "channel": "湖北卫视高清",
    "address": "http://ivi.bupt.edu.cn/hls/hbhd.m3u8"
  },
  {
    "channel": "山东卫视高清",
    "address": "http://ivi.bupt.edu.cn/hls/sdhd.m3u8"
  },
  {
    "channel": "重庆卫视高清",
    "address": "http://ivi.bupt.edu.cn/hls/cqhd.m3u8"
  },
  {
    "channel": "上海纪实高清",
    "address": "http://ivi.bupt.edu.cn/hls/docuchina.m3u8"
  },
  {
    "channel": "金鹰纪实高清",
    "address": "http://ivi.bupt.edu.cn/hls/gedocu.m3u8"
  },
  {
    "channel": "福建东南卫视高清",
    "address": "http://ivi.bupt.edu.cn/hls/dnhd.m3u8"
  },
  {
    "channel": "四川卫视高清",
    "address": "http://ivi.bupt.edu.cn/hls/schd.m3u8"
  },
  {
    "channel": "河北卫视高清",
    "address": "http://ivi.bupt.edu.cn/hls/hebhd.m3u8"
  },
  {
    "channel": "江西卫视高清",
    "address": "http://ivi.bupt.edu.cn/hls/jxhd.m3u8"
  },
  {
    "channel": "河南卫视高清",
    "address": "http://ivi.bupt.edu.cn/hls/hnhd.m3u8"
  },
  {
    "channel": "广西卫视高清",
    "address": "http://ivi.bupt.edu.cn/hls/gxhd.m3u8"
  },
  {
    "channel": "吉林卫视高清",
    "address": "http://ivi.bupt.edu.cn/hls/jlhd.m3u8"
  },
  {
    "channel": "CETV-1高清",
    "address": "http://ivi.bupt.edu.cn/hls/cetv1hd.m3u8"
  },
  {
    "channel": "海南卫视高清",
    "address": "http://ivi.bupt.edu.cn/hls/lyhd.m3u8"
  },
  {
    "channel": "贵州卫视高清",
    "address": "http://ivi.bupt.edu.cn/hls/gzhd.m3u8"
  },
  {
    "channel": "北京文艺高清",
    "address": "http://ivi.bupt.edu.cn/hls/btv2hd.m3u8"
  },
  {
    "channel": "北京影视高清",
    "address": "http://ivi.bupt.edu.cn/hls/btv4hd.m3u8"
  },
  {
    "channel": "北京新闻高清",
    "address": "http://ivi.bupt.edu.cn/hls/btv9hd.m3u8"
  },
  {
    "channel": "北京卡酷少儿高清",
    "address": "http://ivi.bupt.edu.cn/hls/btv9hd.m3u8"
  },
  {
    "channel": "北京冬奥纪实高清",
    "address": "http://ivi.bupt.edu.cn/hls/btv11hd.m3u8"
  },
  {
    "channel": "CGTN高清",
    "address": "http://ivi.bupt.edu.cn/hls/cgtnhd.m3u8"
  },
  {
    "channel": "CGTN DOC高清",
    "address": "http://ivi.bupt.edu.cn/hls/cgtndochd.m3u8"
  },
  {
    "channel": "CHC高清电影",
    "address": "http://ivi.bupt.edu.cn/hls/chchd.m3u8"
  },
  {
    "channel": "CCTV-1综合",
    "address": "http://ivi.bupt.edu.cn/hls/cctv1.m3u8"
  },
  {
    "channel": "CCTV-2财经",
    "address": "http://ivi.bupt.edu.cn/hls/cctv2.m3u8"
  },
  {
    "channel": "CCTV-3综艺",
    "address": "http://ivi.bupt.edu.cn/hls/cctv3.m3u8"
  },
  {
    "channel": "CCTV-4中文国际",
    "address": "http://ivi.bupt.edu.cn/hls/cctv4.m3u8"
  },
  {
    "channel": "CCTV-6电影",
    "address": "http://ivi.bupt.edu.cn/hls/cctv6.m3u8"
  },
  {
    "channel": "CCTV-7国防军事",
    "address": "http://ivi.bupt.edu.cn/hls/cctv7.m3u8"
  },
  {
    "channel": "CCTV-8电视剧",
    "address": "http://ivi.bupt.edu.cn/hls/cctv8.m3u8"
  },
  {
    "channel": "CCTV-9纪录",
    "address": "http://ivi.bupt.edu.cn/hls/cctv9.m3u8"
  },
  {
    "channel": "CCTV-10科教",
    "address": "http://ivi.bupt.edu.cn/hls/cctv10.m3u8"
  },
  {
    "channel": "CCTV-11戏曲",
    "address": "http://ivi.bupt.edu.cn/hls/cctv11.m3u8"
  },
  {
    "channel": "CCTV-12社会与法",
    "address": "http://ivi.bupt.edu.cn/hls/cctv12.m3u8"
  },
  {
    "channel": "CCTV-13新闻",
    "address": "http://ivi.bupt.edu.cn/hls/cctv13.m3u8"
  },
  {
    "channel": "CCTV-14少儿",
    "address": "http://ivi.bupt.edu.cn/hls/cctv14.m3u8"
  },
  {
    "channel": "CCTV-15音乐",
    "address": "http://ivi.bupt.edu.cn/hls/cctv15.m3u8"
  },
  {
    "channel": "CGTN",
    "address": "http://ivi.bupt.edu.cn/hls/cctv16.m3u8"
  },
  {
    "channel": "CCTV-17农业农村",
    "address": "http://ivi.bupt.edu.cn/hls/cctv17.m3u8"
  },
  {
    "channel": "北京卫视",
    "address": "http://ivi.bupt.edu.cn/hls/btv1.m3u8"
  },
  {
    "channel": "北京文艺",
    "address": "http://ivi.bupt.edu.cn/hls/btv2.m3u8"
  },
  {
    "channel": "北京科教",
    "address": "http://ivi.bupt.edu.cn/hls/btv3.m3u8"
  },
  {
    "channel": "北京影视",
    "address": "http://ivi.bupt.edu.cn/hls/btv4.m3u8"
  },
  {
    "channel": "北京财经",
    "address": "http://ivi.bupt.edu.cn/hls/btv5.m3u8"
  },
  {
    "channel": "北京生活",
    "address": "http://ivi.bupt.edu.cn/hls/btv7.m3u8"
  },
  {
    "channel": "北京青年",
    "address": "http://ivi.bupt.edu.cn/hls/btv8.m3u8"
  },
  {
    "channel": "北京新闻",
    "address": "http://ivi.bupt.edu.cn/hls/btv9.m3u8"
  },
  {
    "channel": "北京卡酷少儿",
    "address": "http://ivi.bupt.edu.cn/hls/btv10.m3u8"
  },
  {
    "channel": "北京冬奥纪实",
    "address": "http://ivi.bupt.edu.cn/hls/btv11.m3u8"
  },
  {
    "channel": "湖南卫视",
    "address": "http://ivi.bupt.edu.cn/hls/hunantv.m3u8"
  },
  {
    "channel": "江苏卫视",
    "address": "http://ivi.bupt.edu.cn/hls/jstv.m3u8"
  },
  {
    "channel": "东方卫视",
    "address": "http://ivi.bupt.edu.cn/hls/dftv.m3u8"
  },
  {
    "channel": "深圳卫视",
    "address": "http://ivi.bupt.edu.cn/hls/sztv.m3u8"
  },
  {
    "channel": "安徽卫视",
    "address": "http://ivi.bupt.edu.cn/hls/ahtv.m3u8"
  },
  {
    "channel": "河南卫视",
    "address": "http://ivi.bupt.edu.cn/hls/hntv.m3u8"
  },
  {
    "channel": "陕西卫视",
    "address": "http://ivi.bupt.edu.cn/hls/sxtv.m3u8"
  },
  {
    "channel": "吉林卫视",
    "address": "http://ivi.bupt.edu.cn/hls/jltv.m3u8"
  },
  {
    "channel": "广东卫视",
    "address": "http://ivi.bupt.edu.cn/hls/gdtv.m3u8"
  },
  {
    "channel": "山东卫视",
    "address": "http://ivi.bupt.edu.cn/hls/sdtv.m3u8"
  },
  {
    "channel": "湖北卫视",
    "address": "http://ivi.bupt.edu.cn/hls/hbtv.m3u8"
  },
  {
    "channel": "广西卫视",
    "address": "http://ivi.bupt.edu.cn/hls/gxtv.m3u8"
  },
  {
    "channel": "河北卫视",
    "address": "http://ivi.bupt.edu.cn/hls/hebtv.m3u8"
  },
  {
    "channel": "西藏卫视",
    "address": "http://ivi.bupt.edu.cn/hls/xztv.m3u8"
  },
  {
    "channel": "内蒙古卫视",
    "address": "http://ivi.bupt.edu.cn/hls/nmtv.m3u8"
  },
  {
    "channel": "青海卫视",
    "address": "http://ivi.bupt.edu.cn/hls/qhtv.m3u8"
  },
  {
    "channel": "四川卫视",
    "address": "http://ivi.bupt.edu.cn/hls/sctv.m3u8"
  },
  {
    "channel": "天津卫视",
    "address": "http://ivi.bupt.edu.cn/hls/tjtv.m3u8"
  },
  {
    "channel": "山西卫视",
    "address": "http://ivi.bupt.edu.cn/hls/sxrtv.m3u8"
  },
  {
    "channel": "辽宁卫视",
    "address": "http://ivi.bupt.edu.cn/hls/lntv.m3u8"
  },
  {
    "channel": "厦门卫视",
    "address": "http://ivi.bupt.edu.cn/hls/xmtv.m3u8"
  },
  {
    "channel": "新疆卫视",
    "address": "http://ivi.bupt.edu.cn/hls/xjtv.m3u8"
  },
  {
    "channel": "黑龙江卫视",
    "address": "http://ivi.bupt.edu.cn/hls/hljtv.m3u8"
  },
  {
    "channel": "云南卫视",
    "address": "http://ivi.bupt.edu.cn/hls/yntv.m3u8"
  },
  {
    "channel": "江西卫视",
    "address": "http://ivi.bupt.edu.cn/hls/jxtv.m3u8"
  },
  {
    "channel": "福建东南卫视",
    "address": "http://ivi.bupt.edu.cn/hls/dntv.m3u8"
  },
  {
    "channel": "贵州卫视",
    "address": "http://ivi.bupt.edu.cn/hls/gztv.m3u8"
  },
  {
    "channel": "宁夏卫视",
    "address": "http://ivi.bupt.edu.cn/hls/nxtv.m3u8"
  },
  {
    "channel": "甘肃卫视",
    "address": "http://ivi.bupt.edu.cn/hls/gstv.m3u8"
  },
  {
    "channel": "重庆卫视",
    "address": "http://ivi.bupt.edu.cn/hls/cqtv.m3u8"
  },
  {
    "channel": "兵团卫视",
    "address": "http://ivi.bupt.edu.cn/hls/bttv.m3u8"
  },
  {
    "channel": "延边卫视",
    "address": "http://ivi.bupt.edu.cn/hls/ybtv.m3u8"
  },
  {
    "channel": "三沙卫视",
    "address": "http://ivi.bupt.edu.cn/hls/sstv.m3u8"
  },
  {
    "channel": "海南卫视",
    "address": "http://ivi.bupt.edu.cn/hls/lytv.m3u8"
  },
  {
    "channel": "CETV-1",
    "address": "http://ivi.bupt.edu.cn/hls/cetv1.m3u8"
  },
  {
    "channel": "CETV-3",
    "address": "http://ivi.bupt.edu.cn/hls/cetv3.m3u8"
  },
  {
    "channel": "CETV-4",
    "address": "http://ivi.bupt.edu.cn/hls/cetv4.m3u8"
  },
  {
    "channel": "山东教育",
    "address": "http://ivi.bupt.edu.cn/hls/sdetv.m3u8"
  }
]